MANIFEST.in
README.md
setup.py
dash_ant_design/AutoComplete.py
dash_ant_design/Button.py
dash_ant_design/DashAntDesign.py
dash_ant_design/DatePicker.py
dash_ant_design/Icon.py
dash_ant_design/RangePicker.py
dash_ant_design/Tag.py
dash_ant_design/TimePicker.py
dash_ant_design/Tooltip.py
dash_ant_design/Transfer.py
dash_ant_design/TreeSelect.py
dash_ant_design/__init__.py
dash_ant_design/_imports_.py
dash_ant_design/dash_ant_design.dev.js
dash_ant_design/dash_ant_design.min.js
dash_ant_design/metadata.json
dash_ant_design/package.json
dash_ant_design.egg-info/PKG-INFO
dash_ant_design.egg-info/SOURCES.txt
dash_ant_design.egg-info/dependency_links.txt
dash_ant_design.egg-info/top_level.txt