Metadata-Version: 1.0
Name: dash-ant-design
Version: 3.0.0.12
Summary: Dash Ant Design
Home-page: UNKNOWN
Author: Holger Amort holgeramort@gmail.com
Author-email: UNKNOWN
License: UNKNOWN
Platform: UNKNOWN
